sinaraml/__init__.py
sinaraml/_version.py
sinaraml/org_manager.py
sinaraml/sinaraml.py
sinaraml-2025.6.25.dist-info/METADATA
sinaraml-2025.6.25.dist-info/WHEEL
sinaraml-2025.6.25.dist-info/entry_points.txt
sinaraml-2025.6.25.dist-info/RECORD
