Metadata-Version: 2.4
Name: sinaraml
Version: 2025.6.25
Summary: SinaraML
Project-URL: Homepage, https://github.com/4-DS/sinaraml
Author-email: sinaraml <sinaraml.official@gmail.com>
Keywords: cli,sinaraml
Classifier: License :: OSI Approved :: MIT License
Classifier: Operating System :: OS Independent
Classifier: Programming Language :: Python :: 3.6
Classifier: Programming Language :: Python :: 3.7
Classifier: Programming Language :: Python :: 3.8
Classifier: Programming Language :: Python :: 3.9
Classifier: Programming Language :: Python :: 3.10
Classifier: Programming Language :: Python :: 3.11
Classifier: Programming Language :: Python :: 3.12
Classifier: Programming Language :: Python :: Implementation :: CPython
Classifier: Topic :: Scientific/Engineering :: Artificial Intelligence
Requires-Python: >=3.6
Requires-Dist: docker
Requires-Dist: importlib-metadata; python_version >= '3.6'
Requires-Dist: requests
Requires-Dist: tqdm
